LICENSE
MANIFEST.in
README.md
setup.py
bin/cconstruct
complexconstructor/CB_icon.png
complexconstructor/CB_icon_sm.png
complexconstructor/__init__.py
complexconstructor/argparser.py
complexconstructor/helpText.py
complexconstructor/interface.py
complexconstructor/logProgress.py
complexconstructor/utilities.py
complexconstructor.egg-info/PKG-INFO
complexconstructor.egg-info/SOURCES.txt
complexconstructor.egg-info/dependency_links.txt
complexconstructor.egg-info/requires.txt
complexconstructor.egg-info/top_level.txt