Metadata-Version: 2.1
Name: complexconstructor
Version: 0.1.6
Summary: Generate macrocomplexes superimposing       paired interacting elements.
Home-page: https://github.com/Argonvi/SBI-PYT_Project
Author: Paula Gomis Rosa, Arturo González Vilanova, Marta López Balastegui
Author-email: marta.lopez01@estudiant.upf.edu, paula.gomis01@estudiant.upf.edu, arturo.gonzalez01@estudiant.upf.edu
License: MIT
Keywords: macrocomplex bioinformatics structural pdb protein
Platform: UNKNOWN
Classifier: Programming Language :: Python :: 3
Classifier: License :: OSI Approved :: MIT License
